__init__.py
enmet/__init__.py
enmet/common.py
enmet/countries.py
enmet/entities.py
enmet/pages.py
enmet/search.py
enmet-0.9.1.dist-info/METADATA
enmet-0.9.1.dist-info/WHEEL
enmet-0.9.1.dist-info/top_level.txt
enmet-0.9.1.dist-info/RECORD
