Metadata-Version: 2.1
Name: enmet
Version: 0.9.1
Summary: Python API for Encyclopaedia Metallum (The Metal Archives) website.
Author: Łukasz Jakubowski
License: GPL-3.0-or-later
Project-URL: Documentation, https://github.com/lukjak/enmet/blob/master/README.md
Project-URL: Repository, https://github.com/lukjak/enmet
Classifier: Development Status :: 5 - Production/Stable
Classifier: Natural Language :: English
Classifier: Operating System :: OS Independent
Classifier: Topic :: Internet
Requires-Python: >=3.10
Requires-Dist: beautifulsoup4
Requires-Dist: requests
Requires-Dist: requests-cache
Provides-Extra: test
Requires-Dist: pytest ; extra == 'test'
Requires-Dist: pytest-mock ; extra == 'test'
